vllmctl/__main__.py
vllmctl/cli.py
vllmctl/core/__init__.py
vllmctl/core/forward.py
vllmctl/core/launcher.py
vllmctl/core/parallel_utils.py
vllmctl/core/platform_mac.py
vllmctl/core/ssh_utils.py
vllmctl/core/vllm_probe.py
vllmctl-0.2.1.dist-info/METADATA
vllmctl-0.2.1.dist-info/WHEEL
vllmctl-0.2.1.dist-info/entry_points.txt
vllmctl-0.2.1.dist-info/RECORD
