Metadata-Version: 2.1
Name: vllmctl
Version: 0.2.1
Summary: CLI tool for launching and managing vllm model servers via SSH and tmux
License: MIT
Author: vllmctl
Author-email: adefful46@gmail.com
Requires-Python: >=3.8,<4.0
Classifier: License :: OSI Approved :: MIT License
Classifier: Programming Language :: Python :: 3
Classifier: Programming Language :: Python :: 3.8
Classifier: Programming Language :: Python :: 3.9
Classifier: Programming Language :: Python :: 3.10
Classifier: Programming Language :: Python :: 3.11
Classifier: Programming Language :: Python :: 3.12
Requires-Dist: psutil (>=5.9.0)
Requires-Dist: requests (>=2.28.0)
Requires-Dist: rich (>=13.0.0)
Requires-Dist: typer (>=0.9.0)
